py7za/__init__.py
py7za/_asyncio_pool.py
py7za/_cpu_count.py
py7za/_nice_size.py
py7za/_py7za.py
py7za/_version.py
py7za/groups.json
py7za/py7za_box.py
py7za/bin/7za-license.txt
py7za/bin/7za.exe
py7za/bin/GNU_LGPL.txt
py7za-0.2.6.dist-info/LICENSE.txt
py7za-0.2.6.dist-info/METADATA
py7za-0.2.6.dist-info/WHEEL
py7za-0.2.6.dist-info/entry_points.txt
py7za-0.2.6.dist-info/top_level.txt
py7za-0.2.6.dist-info/RECORD
