Metadata-Version: 2.1
Name: py7za
Version: 0.2.6
Summary: Description
Home-page: https://gitlab.com/Jaap.vanderVelde/py7za
Download-URL: https://gitlab.com/Jaap.vanderVelde/py7za/repository/archive.zip?ref=0.2.6
Author: BMT, Jaap van der Velde
Author-email: jaap.vandervelde@bmtglobal.com
License: MIT
Keywords: package
Classifier: Development Status :: 4 - Beta
Classifier: Intended Audience :: Developers
Classifier: Topic :: Software Development :: Build Tools
Classifier: License :: OSI Approved :: MIT License
Classifier: Programming Language :: Python :: 3.8
Requires-Python: >=3.8,<=3.10
License-File: LICENSE.txt
Provides-Extra: box
Requires-Dist: conffu ; extra == 'box'
Provides-Extra: dev
Requires-Dist: mkdocs ; extra == 'dev'
